mobile_payments/__init__.py
mobile_payments/constants.py
mobile_payments/open_api.py
mobile_payments/vodacom.py
mobile_payments-0.1.2.dist-info/LICENSE
mobile_payments-0.1.2.dist-info/WHEEL
mobile_payments-0.1.2.dist-info/METADATA
mobile_payments-0.1.2.dist-info/RECORD
